upload_socials/__init__.py
upload_socials/uploadyt/channeldashboard.png
upload_socials/uploadyt/create.png
upload_socials/uploadyt/create2.png
upload_socials/uploadyt/filename.png
upload_socials/uploadyt/monetizeactive.png
upload_socials/uploadyt/monetizedone.png
upload_socials/uploadyt/monetizenone.png
upload_socials/uploadyt/monetizeon.png
upload_socials/uploadyt/monetizepublic.png
upload_socials/uploadyt/monetizeselect.png
upload_socials/uploadyt/monetizesubmit.png
upload_socials/uploadyt/next.png
upload_socials/uploadyt/oops.png
upload_socials/uploadyt/oops2.png
upload_socials/uploadyt/processing.png
upload_socials/uploadyt/publish.png
upload_socials/uploadyt/publish2.png
upload_socials/uploadyt/select.png
upload_socials/uploadyt/select2.png
upload_socials/uploadyt/showmore.png
upload_socials/uploadyt/tags.png
upload_socials/uploadyt/tell.png
upload_socials/uploadyt/thumbnail.png
upload_socials/uploadyt/thumbnail2.png
upload_socials/uploadyt/title.png
upload_socials/uploadyt/uploadvids.png
upload_socials/uploadyt/uploadvids2.png
upload_socials-1.1.1.dist-info/licenses/LICENSE
upload_socials-1.1.1.dist-info/METADATA
upload_socials-1.1.1.dist-info/WHEEL
upload_socials-1.1.1.dist-info/top_level.txt
upload_socials-1.1.1.dist-info/RECORD
