Metadata-Version: 2.4
Name: upload-socials
Version: 1.1.1
Summary: A Python library to automate video uploads to YouTube.
Home-page: https://github.com/AMAMazing/upload-socials
Author: AMAMazing
Author-email: alexmalone489@gmail.com
Classifier: Programming Language :: Python :: 3
Classifier: License :: OSI Approved :: MIT License
Classifier: Operating System :: OS Independent
Requires-Python: >=3.6
License-File: LICENSE
Requires-Dist: pyautogui
Requires-Dist: pywin32
Requires-Dist: optimisewait
Requires-Dist: smartpaste
Dynamic: author
Dynamic: author-email
Dynamic: classifier
Dynamic: description
Dynamic: description-content-type
Dynamic: home-page
Dynamic: license-file
Dynamic: requires-dist
Dynamic: requires-python
Dynamic: summary
